Workbook
Name Client: 'Client lookup table'!$A$2:$E$67
Name Product: 'Product lookup table'!$A$2:$E$20
Name Prowizje: 'Założenia (Assumptions)'!$B$4:$C$7

Sheet Dane surowe (Raw data)
A1: ID zamów. (Order ID) | B1: Data zamów. (Order date) | C1: Produkt (Product) | D1: Kanał sprzedaży (Marketplace) | E1: ID klienta (Client ID) | F1: Miasto (City) | G1: Kod poczt. (Postcode) | H1: Cena jedn. (Price unit) | I1: Ilość (Quant.) | J1: Zniżka (Discount) | K1: Przychód brutto (Revenue)
A2: ORD0001 | B2: 45941 | C2: Namiot | D2: Empik Marketplace | E2: CUST4269 | F2: Poznań | G2: 51-418 | H2: 632.92143 | I2: 2 | J2: 0 | K2: =(Raw_Data[[#This Row],[Cena jedn. (Price unit)]]-(Raw_Data[[#This Row],[Cena jedn. (Price unit)]]*Raw_Data[[#This Row],[Zniżka (Discount)]]))*Raw_Data[[#This Row],[Ilość (Quant.)]] -> 1265.8429
A3: ORD0002 | B3: 45750 | C3: Buty trekkingowe | D3: Amazon | E3: CUST2762 | F3: Gdańsk | G3: 49-873 | H3: 594.41857 | I3: 4 | J3: 0 | K3: =(Raw_Data[[#This Row],[Cena jedn. (Price unit)]]-(Raw_Data[[#This Row],[Cena jedn. (Price unit)]]*Raw_Data[[#This Row],[Zniżka (Discount)]]))*Raw_Data[[#This Row],[Ilość (Quant.)]] -> 2377.6743
A4: ORD0003 | B4: 45807 | C4: Żel pod prysznic | D4: Allegro | E4: CUST7053 | F4: Gdańsk | G4: 68-417 | H4: 7.9344444 | I4: 3 | J4: 0 | K4: =(Raw_Data[[#This Row],[Cena jedn. (Price unit)]]-(Raw_Data[[#This Row],[Cena jedn. (Price unit)]]*Raw_Data[[#This Row],[Zniżka (Discount)]]))*Raw_Data[[#This Row],[Ilość (Quant.)]] -> 23.803333
A5: ORD0004 | B5: 45715 | C5: Powerbank | D5: Amazon | E5: CUST7053 | F5: Gdańsk | G5: 68-417 | H5: 99.620435 | I5: 1 | J5: 0 | K5: =(Raw_Data[[#This Row],[Cena jedn. (Price unit)]]-(Raw_Data[[#This Row],[Cena jedn. (Price unit)]]*Raw_Data[[#This Row],[Zniżka (Discount)]]))*Raw_Data[[#This Row],[Ilość (Quant.)]] -> 99.620435
A6: ORD0005 | B6: 45977 | C6: Buty trekkingowe | D6: Amazon | E6: CUST3810 | F6: Poznań | G6: 39-844 | H6: 509.82571 | I6: 2 | J6: 0 | K6: =(Raw_Data[[#This Row],[Cena jedn. (Price unit)]]-(Raw_Data[[#This Row],[Cena jedn. (Price unit)]]*Raw_Data[[#This Row],[Zniżka (Discount)]]))*Raw_Data[[#This Row],[Ilość (Quant.)]] -> 1019.6514
A7: ORD0006 | B7: 45946 | C7: Szampon | D7: Allegro | E7: CUST3810 | F7: Poznań | G7: 39-844 | H7: 8.1277778 | I7: 5 | J7: 0.1 | K7: =(Raw_Data[[#This Row],[Cena jedn. (Price unit)]]-(Raw_Data[[#This Row],[Cena jedn. (Price unit)]]*Raw_Data[[#This Row],[Zniżka (Discount)]]))*Raw_Data[[#This Row],[Ilość (Quant.)]] -> 36.575
A8: ORD0007 | B8: 45807 | C8: Świeca zapachowa | D8: Allegro | E8: CUST3810 | F8: Poznań | G8: 39-844 | H8: 46.808182 | I8: 4 | J8: 0 | K8: =(Raw_Data[[#This Row],[Cena jedn. (Price unit)]]-(Raw_Data[[#This Row],[Cena jedn. (Price unit)]]*Raw_Data[[#This Row],[Zniżka (Discount)]]))*Raw_Data[[#This Row],[Ilość (Quant.)]] -> 187.23273
A9: ORD0008 | B9: 45753 | C9: Krem do twarzy | D9: Amazon | E9: CUST3810 | F9: Poznań | G9: 39-844 | H9: 60.434444 | I9: 1 | J9: 0.15 | K9: =(Raw_Data[[#This Row],[Cena jedn. (Price unit)]]-(Raw_Data[[#This Row],[Cena jedn. (Price unit)]]*Raw_Data[[#This Row],[Zniżka (Discount)]]))*Raw_Data[[#This Row],[Ilość (Quant.)]] -> 51.369278
A10: ORD0009 | B10: 45884 | C10: Serum | D10: Amazon | E10: CUST3810 | F10: Poznań | G10: 39-844 | H10: 87.016667 | I10: 4 | J10: 0.05 | K10: =(Raw_Data[[#This Row],[Cena jedn. (Price unit)]]-(Raw_Data[[#This Row],[Cena jedn. (Price unit)]]*Raw_Data[[#This Row],[Zniżka (Discount)]]))*Raw_Data[[#This Row],[Ilość (Quant.)]] -> 330.66333
A11: ORD0010 | B11: 45930 | C11: Namiot | D11: Empik Marketplace | E11: CUST6724 | F11: Kraków | G11: 20-651 | H11: 566.70429 | I11: 4 | J11: 0 | K11: =(Raw_Data[[#This Row],[Cena jedn. (Price unit)]]-(Raw_Data[[#This Row],[Cena jedn. (Price unit)]]*Raw_Data[[#This Row],[Zniżka (Discount)]]))*Raw_Data[[#This Row],[Ilość (Quant.)]] -> 2266.8171
A12: ORD0011 | B12: 45676 | C12: Paleta cieni | D12: Allegro | E12: CUST6724 | F12: Kraków | G12: 20-651 | H12: 98.567778 | I12: 1 | J12: 0.1 | K12: =(Raw_Data[[#This Row],[Cena jedn. (Price unit)]]-(Raw_Data[[#This Row],[Cena jedn. (Price unit)]]*Raw_Data[[#This Row],[Zniżka (Discount)]]))*Raw_Data[[#This Row],[Ilość (Quant.)]] -> 88.711
A13: ORD0012 | B13: 46009 | C13: Poduszka dekoracyjna | D13: Amazon | E13: CUST6724 | F13: Kraków | G13: 20-651 | H13: 61.630909 | I13: 4 | J13: 0.2 | K13: =(Raw_Data[[#This Row],[Cena jedn. (Price unit)]]-(Raw_Data[[#This Row],[Cena jedn. (Price unit)]]*Raw_Data[[#This Row],[Zniżka (Discount)]]))*Raw_Data[[#This Row],[Ilość (Quant.)]] -> 197.21891
... A201: ORD0200 | B201: 45999 | C201: Olejek | D201: Amazon | E201: CUST7053 | F201: Gdańsk | G201: 68-417 | H201: 12.238889 | I201: 5 | J201: 0.2 | K201: =(Raw_Data[[#This Row],[Cena jedn. (Price unit)]]-(Raw_Data[[#This Row],[Cena jedn. (Price unit)]]*Raw_Data[[#This Row],[Zniżka (Discount)]]))*Raw_Data[[#This Row],[Ilość (Quant.)]] -> 48.955556
H202: =SUBTOTAL(101,Raw_Data[Cena jedn. (Price unit)]) -> 148.98106 | I202: =SUBTOTAL(109,Raw_Data[Ilość (Quant.)]) -> 478 | J202: =SUBTOTAL(101,Raw_Data[Zniżka (Discount)]) -> 0.052614379 | K202: =SUBTOTAL(101,Raw_Data[Przychód brutto (Revenue)]) -> 426.67789

Sheet Client lookup table
A1: Klient (Client) | B1: Sektor (Sector) | C1: Data pierw. zam. (First time ord.) | D1: Wart. żyć. (LTV Revenue) | E1: Wart. żyć. (LTV Gross profit)
A2: CUST1668 | B2: Klient prywatny | C2: =_xlfn.MINIFS(Raw_Data[Data zamów. (Order date)],Raw_Data[ID klienta (Client ID)],A2) -> 45737 | D2: =SUMIF(Raw_Data[ID klienta (Client ID)],A2,Raw_Data[Przychód brutto (Revenue)]) -> 1181.1327 | E2: =SUMIF(Raw_Data[ID klienta (Client ID)],A2,Processed_data[Zysk brutto (Gross profit)]) -> 228.84599
A3: CUST7768 | B3: Klient prywatny | C3: =_xlfn.MINIFS(Raw_Data[Data zamów. (Order date)],Raw_Data[ID klienta (Client ID)],A3) -> 45686 | D3: =SUMIF(Raw_Data[ID klienta (Client ID)],A3,Raw_Data[Przychód brutto (Revenue)]) -> 4376.2597 | E3: =SUMIF(Raw_Data[ID klienta (Client ID)],A3,Processed_data[Zysk brutto (Gross profit)]) -> 1127.4479
A4: CUST8117 | B4: Home office | C4: =_xlfn.MINIFS(Raw_Data[Data zamów. (Order date)],Raw_Data[ID klienta (Client ID)],A4) -> 45665 | D4: =SUMIF(Raw_Data[ID klienta (Client ID)],A4,Raw_Data[Przychód brutto (Revenue)]) -> 565.16075 | E4: =SUMIF(Raw_Data[ID klienta (Client ID)],A4,Processed_data[Zysk brutto (Gross profit)]) -> 137.39877
A5: CUST7722 | B5: Klient prywatny | C5: =_xlfn.MINIFS(Raw_Data[Data zamów. (Order date)],Raw_Data[ID klienta (Client ID)],A5) -> 45685 | D5: =SUMIF(Raw_Data[ID klienta (Client ID)],A5,Raw_Data[Przychód brutto (Revenue)]) -> 1417.3545 | E5: =SUMIF(Raw_Data[ID klienta (Client ID)],A5,Processed_data[Zysk brutto (Gross profit)]) -> 213.08835
A6: CUST5826 | B6: Klient prywatny | C6: =_xlfn.MINIFS(Raw_Data[Data zamów. (Order date)],Raw_Data[ID klienta (Client ID)],A6) -> 45797 | D6: =SUMIF(Raw_Data[ID klienta (Client ID)],A6,Raw_Data[Przychód brutto (Revenue)]) -> 1486.201 | E6: =SUMIF(Raw_Data[ID klienta (Client ID)],A6,Processed_data[Zysk brutto (Gross profit)]) -> 322.78927
A7: CUST1571 | B7: Home office | C7: =_xlfn.MINIFS(Raw_Data[Data zamów. (Order date)],Raw_Data[ID klienta (Client ID)],A7) -> 45735 | D7: =SUMIF(Raw_Data[ID klienta (Client ID)],A7,Raw_Data[Przychód brutto (Revenue)]) -> 2225.9973 | E7: =SUMIF(Raw_Data[ID klienta (Client ID)],A7,Processed_data[Zysk brutto (Gross profit)]) -> 377.31246
A8: CUST4479 | B8: Klient prywatny | C8: =_xlfn.MINIFS(Raw_Data[Data zamów. (Order date)],Raw_Data[ID klienta (Client ID)],A8) -> 45756 | D8: =SUMIF(Raw_Data[ID klienta (Client ID)],A8,Raw_Data[Przychód brutto (Revenue)]) -> 477.70632 | E8: =SUMIF(Raw_Data[ID klienta (Client ID)],A8,Processed_data[Zysk brutto (Gross profit)]) -> 129.00993
A9: CUST4965 | B9: Klient prywatny | C9: =_xlfn.MINIFS(Raw_Data[Data zamów. (Order date)],Raw_Data[ID klienta (Client ID)],A9) -> 45696 | D9: =SUMIF(Raw_Data[ID klienta (Client ID)],A9,Raw_Data[Przychód brutto (Revenue)]) -> 508.14192 | E9: =SUMIF(Raw_Data[ID klienta (Client ID)],A9,Processed_data[Zysk brutto (Gross profit)]) -> 82.09421
A10: CUST2870 | B10: Home office | C10: =_xlfn.MINIFS(Raw_Data[Data zamów. (Order date)],Raw_Data[ID klienta (Client ID)],A10) -> 45784 | D10: =SUMIF(Raw_Data[ID klienta (Client ID)],A10,Raw_Data[Przychód brutto (Revenue)]) -> 1475.3017 | E10: =SUMIF(Raw_Data[ID klienta (Client ID)],A10,Processed_data[Zysk brutto (Gross profit)]) -> 500.30743
A11: CUST7044 | B11: Klient prywatny | C11: =_xlfn.MINIFS(Raw_Data[Data zamów. (Order date)],Raw_Data[ID klienta (Client ID)],A11) -> 45855 | D11: =SUMIF(Raw_Data[ID klienta (Client ID)],A11,Raw_Data[Przychód brutto (Revenue)]) -> 3369.4908 | E11: =SUMIF(Raw_Data[ID klienta (Client ID)],A11,Processed_data[Zysk brutto (Gross profit)]) -> 921.88289
A12: CUST1402 | B12: Klient prywatny | C12: =_xlfn.MINIFS(Raw_Data[Data zamów. (Order date)],Raw_Data[ID klienta (Client ID)],A12) -> 45704 | D12: =SUMIF(Raw_Data[ID klienta (Client ID)],A12,Raw_Data[Przychód brutto (Revenue)]) -> 2555.2515 | E12: =SUMIF(Raw_Data[ID klienta (Client ID)],A12,Processed_data[Zysk brutto (Gross profit)]) -> 672.24434
A13: CUST3365 | B13: Klient prywatny | C13: =_xlfn.MINIFS(Raw_Data[Data zamów. (Order date)],Raw_Data[ID klienta (Client ID)],A13) -> 45805 | D13: =SUMIF(Raw_Data[ID klienta (Client ID)],A13,Raw_Data[Przychód brutto (Revenue)]) -> 382.67974 | E13: =SUMIF(Raw_Data[ID klienta (Client ID)],A13,Processed_data[Zysk brutto (Gross profit)]) -> 79.540239
... A67: CUST1505 | B67: Home office | C67: =_xlfn.MINIFS(Raw_Data[Data zamów. (Order date)],Raw_Data[ID klienta (Client ID)],A67) -> 45899 | D67: =SUMIF(Raw_Data[ID klienta (Client ID)],A67,Raw_Data[Przychód brutto (Revenue)]) -> 429.18693 | E67: =SUMIF(Raw_Data[ID klienta (Client ID)],A67,Processed_data[Zysk brutto (Gross profit)]) -> 159.18693

Sheet Product lookup table
A1: Produkt (Product) | B1: Kategoria (Category | C1: Koszty (COGS) | D1: Min. cena (Min. price) | E1: Średnia marża (Average margin)
A2: Głośnik | B2: Elektronika | C2: 130 | D2: =C2*100/92 -> 141.30435 | E2: =AVERAGEIF(Raw_Data[Produkt (Product)],'Product lookup table'!A2,Processed_data[Marża (Margin)]) -> 0.12701551
A3: Klawiatura | B3: Elektronika | C3: 110 | D3: =C3*100/92 -> 119.56522 | E3: =AVERAGEIF(Raw_Data[Produkt (Product)],'Product lookup table'!A3,Processed_data[Marża (Margin)]) -> 0.057354932
A4: Myszka | B4: Elektronika | C4: 70 | D4: =C4*100/92 -> 76.086957 | E4: =AVERAGEIF(Raw_Data[Produkt (Product)],'Product lookup table'!A4,Processed_data[Marża (Margin)]) -> 0.056122823
A5: Powerbank | B5: Elektronika | C5: 80 | D5: =C5*100/92 -> 86.956522 | E5: =AVERAGEIF(Raw_Data[Produkt (Product)],'Product lookup table'!A5,Processed_data[Marża (Margin)]) -> 0.11714093
A6: Kubek | B6: Home | C6: 9 | D6: =C6*100/55 -> 16.363636 | E6: =AVERAGEIF(Raw_Data[Produkt (Product)],'Product lookup table'!A6,Processed_data[Marża (Margin)]) -> 0.47783437
A7: Poduszka dekoracyjna | B7: Home | C7: 30 | D7: =C7*100/55 -> 54.545455 | E7: =AVERAGEIF(Raw_Data[Produkt (Product)],'Product lookup table'!A7,Processed_data[Marża (Margin)]) -> 0.45503777
A8: Świeca zapachowa | B8: Home | C8: 20 | D8: =C8*100/55 -> 36.363636 | E8: =AVERAGEIF(Raw_Data[Produkt (Product)],'Product lookup table'!A8,Processed_data[Marża (Margin)]) -> 0.45231193
A9: Wazon szklany | B9: Home | C9: 15 | D9: =C9*100/55 -> 27.272727 | E9: =AVERAGEIF(Raw_Data[Produkt (Product)],'Product lookup table'!A9,Processed_data[Marża (Margin)]) -> 0.46015582
A10: Krem do twarzy | B10: Kosmetyki | C10: 25 | D10: =C10*100/45 -> 55.555556 | E10: =AVERAGEIF(Raw_Data[Produkt (Product)],'Product lookup table'!A10,Processed_data[Marża (Margin)]) -> 0.50694396
A11: Olejek | B11: Kosmetyki | C11: 5 | D11: =C11*100/45 -> 11.111111 | E11: =AVERAGEIF(Raw_Data[Produkt (Product)],'Product lookup table'!A11,Processed_data[Marża (Margin)]) -> 0.54897858
A12: Paleta cieni | B12: Kosmetyki | C12: 40 | D12: =C12*100/45 -> 88.888889 | E12: =AVERAGEIF(Raw_Data[Produkt (Product)],'Product lookup table'!A12,Processed_data[Marża (Margin)]) -> 0.51517469
A13: Serum | B13: Kosmetyki | C13: 30 | D13: =C13*100/45 -> 66.666667 | E13: =AVERAGEIF(Raw_Data[Produkt (Product)],'Product lookup table'!A13,Processed_data[Marża (Margin)]) -> 0.53510866
A14: Szampon | B14: Kosmetyki | C14: 3.5 | D14: =C14*100/45 -> 7.7777778 | E14: =AVERAGEIF(Raw_Data[Produkt (Product)],'Product lookup table'!A14,Processed_data[Marża (Margin)]) -> 0.55294059
A15: Żel pod prysznic | B15: Kosmetyki | C15: 2.5 | D15: =C15*100/45 -> 5.5555556 | E15: =AVERAGEIF(Raw_Data[Produkt (Product)],'Product lookup table'!A15,Processed_data[Marża (Margin)]) -> 0.56505638
A16: Bidon | B16: Outdoor | C16: 15 | D16: =C16*100/70 -> 21.428571 | E16: =AVERAGEIF(Raw_Data[Produkt (Product)],'Product lookup table'!A16,Processed_data[Marża (Margin)]) -> 0.33971623
A17: Buty trekkingowe | B17: Outdoor | C17: 310 | D17: =C17*100/70 -> 442.85714 | E17: =AVERAGEIF(Raw_Data[Produkt (Product)],'Product lookup table'!A17,Processed_data[Marża (Margin)]) -> 0.29516153
A18: Latarka | B18: Outdoor | C18: 28 | D18: =C18*100/70 -> 40 | E18: =AVERAGEIF(Raw_Data[Produkt (Product)],'Product lookup table'!A18,Processed_data[Marża (Margin)]) -> 0.29398552
A19: Namiot | B19: Outdoor | C19: 360 | D19: =C19*100/70 -> 514.28571 | E19: =AVERAGEIF(Raw_Data[Produkt (Product)],'Product lookup table'!A19,Processed_data[Marża (Margin)]) -> 0.28764561
A20: Śpiwór | B20: Outdoor | C20: 270 | D20: =C20*100/70 -> 385.71429 | E20: =AVERAGEIF(Raw_Data[Produkt (Product)],'Product lookup table'!A20,Processed_data[Marża (Margin)]) -> 0.32409368

Sheet Założenia (Assumptions)
B2: Prowizje platform
B3: Kanał sprzedaży (Marketplace) | C3: Prowizja (Commission)
B4: Allegro | C4: 0.08
B5: Amazon | C5: 0.12
B6: Empik Marketplace | C6: 0.1
B7: Shopify | C7: 0
B8: źródło: oparte o orientacyjne stawki rynkowe (maj 2026), zmodyfikowane w celu zróżnicowania wyników analizy.
B10: Zakres danych
B11: Dane obejmują okres styczeń-grudzień 2025
B12: Brak uwzględnienia kosztów operacyjnych (wysyłka, magazyn, marketing)
B14: Dane cenowe
B15: Ceny minimalne ustalone jako COGS×100/45 dla kategorii kosmetyki, ×100/55 dla home, ×100/70 dla outdoor, ×100/92 dla elektroniki - gwarancja minimalnej marży odpowiednio ~55%, ~45%, ~30%, ~8%
B16: Ceny sprzedaży generowane losowo jako cena minimalna + 0-40% narzutu
B17: Zniżki generowane losowo
B18: Stały COGS dla każdego produktu podany w tabeli Product Lookup
B20: Definicje wskaźników
B21: Zysk brutto = przychód brutto - (COGS × ilość) - prowizja platformy
B22: Marża = zysk brutto / przychód brutto
... B24: LTV (Gross Profit) = suma zysku brutto ze wszystkich zamówień klienta

Sheet Dane przetw. (Processed data)
A1: ID zamów. (Order ID) | B1: ID klienta (Client ID) | C1: Kategoria (Category) | D1: Produkt (Product) | E1: Kanał sprzedaży (Marketplace) | F1: Miasto (City) | G1: Ilość (Quant.) | H1: Przychód brutto (Revenue) | I1: Zysk brutto (Gross profit) | J1: Marża (Margin) | K1: Kat. marży (Margin category) | L1: Miesiąc (Month) | M1: Miesiąc (Month)2 | N1: Kwartał (Quarter)
A2: =Raw_Data[[#This Row],[ID zamów. (Order ID)]] -> ORD0001 | B2: =Raw_Data[[#This Row],[ID klienta (Client ID)]] -> CUST4269 | C2: =_xlfn.XLOOKUP(Raw_Data[[#This Row],[Produkt (Product)]],'Product lookup table'!$A$2:$A$20,'Product lookup table'!$B$2:$B$20) -> Outdoor | D2: =Raw_Data[[#This Row],[Produkt (Product)]] -> Namiot | E2: =Raw_Data[[#This Row],[Kanał sprzedaży (Marketplace)]] -> Empik Marketplace | F2: =Raw_Data[[#This Row],[Miasto (City)]] -> Poznań | G2: =Raw_Data[[#This Row],[Ilość (Quant.)]] -> 2 | H2: =Raw_Data[[#This Row],[Przychód brutto (Revenue)]] -> 1265.8429 | I2: =(Raw_Data[[#This Row],[Przychód brutto (Revenue)]]-_xlfn.XLOOKUP(Raw_Data[[#This Row],[Produkt (Product)]],'Product lookup table'!$A$2:$A$20,'Product lookup table'!$C$2:$C$20)*Raw_Data[[#This Row],[Ilość (Quant.)]]) - (Raw_Data[[#This Row],[Przychód brutto (Revenue)]]*_xlfn.XLOOKUP(Processed_data[[#This Row],[Kanał sprzedaży (Marketplace)]],'Założenia (Assumptions)'!$B$4:$B$7,'Założenia (Assumptions)'!$C$4:$C$7)) -> 419.25857 | J2: =Processed_data[[#This Row],[Zysk brutto (Gross profit)]]/Processed_data[[#This Row],[Przychód brutto (Revenue)]] -> 0.33120902 | K2: =IF(Processed_data[[#This Row],[Marża (Margin)]]>0.6,"wysoka",IF(Processed_data[[#This Row],[Marża (Margin)]]>0.3,"średnia","niska")) -> średnia | L2: =MONTH(Raw_Data[[#This Row],[Data zamów. (Order date)]]) -> 10 | M2: =TEXT(Raw_Data[[#This Row],[Data zamów. (Order date)]], "MMMM") -> październik | N2: =IF(Processed_data[[#This Row],[Miesiąc (Month)]]<=3,1,IF(Processed_data[[#This Row],[Miesiąc (Month)]]<=6,2,IF(Processed_data[[#This Row],[Miesiąc (Month)]]<=9,3,4))) -> 4
A3: =Raw_Data[[#This Row],[ID zamów. (Order ID)]] -> ORD0002 | B3: =Raw_Data[[#This Row],[ID klienta (Client ID)]] -> CUST2762 | C3: =_xlfn.XLOOKUP(Raw_Data[[#This Row],[Produkt (Product)]],'Product lookup table'!$A$2:$A$20,'Product lookup table'!$B$2:$B$20) -> Outdoor | D3: =Raw_Data[[#This Row],[Produkt (Product)]] -> Buty trekkingowe | E3: =Raw_Data[[#This Row],[Kanał sprzedaży (Marketplace)]] -> Amazon | F3: =Raw_Data[[#This Row],[Miasto (City)]] -> Gdańsk | G3: =Raw_Data[[#This Row],[Ilość (Quant.)]] -> 4 | H3: =Raw_Data[[#This Row],[Przychód brutto (Revenue)]] -> 2377.6743 | I3: =(Raw_Data[[#This Row],[Przychód brutto (Revenue)]]-_xlfn.XLOOKUP(Raw_Data[[#This Row],[Produkt (Product)]],'Product lookup table'!$A$2:$A$20,'Product lookup table'!$C$2:$C$20)*Raw_Data[[#This Row],[Ilość (Quant.)]]) - (Raw_Data[[#This Row],[Przychód brutto (Revenue)]]*_xlfn.XLOOKUP(Processed_data[[#This Row],[Kanał sprzedaży (Marketplace)]],'Założenia (Assumptions)'!$B$4:$B$7,'Założenia (Assumptions)'!$C$4:$C$7)) -> 852.35337 | J3: =Processed_data[[#This Row],[Zysk brutto (Gross profit)]]/Processed_data[[#This Row],[Przychód brutto (Revenue)]] -> 0.35848197 | K3: =IF(Processed_data[[#This Row],[Marża (Margin)]]>0.6,"wysoka",IF(Processed_data[[#This Row],[Marża (Margin)]]>0.3,"średnia","niska")) -> średnia | L3: =MONTH(Raw_Data[[#This Row],[Data zamów. (Order date)]]) -> 4 | M3: =TEXT(Raw_Data[[#This Row],[Data zamów. (Order date)]], "MMMM") -> kwiecień | N3: =IF(Processed_data[[#This Row],[Miesiąc (Month)]]<=3,1,IF(Processed_data[[#This Row],[Miesiąc (Month)]]<=6,2,IF(Processed_data[[#This Row],[Miesiąc (Month)]]<=9,3,4))) -> 2
A4: =Raw_Data[[#This Row],[ID zamów. (Order ID)]] -> ORD0003 | B4: =Raw_Data[[#This Row],[ID klienta (Client ID)]] -> CUST7053 | C4: =_xlfn.XLOOKUP(Raw_Data[[#This Row],[Produkt (Product)]],'Product lookup table'!$A$2:$A$20,'Product lookup table'!$B$2:$B$20) -> Kosmetyki | D4: =Raw_Data[[#This Row],[Produkt (Product)]] -> Żel pod prysznic | E4: =Raw_Data[[#This Row],[Kanał sprzedaży (Marketplace)]] -> Allegro | F4: =Raw_Data[[#This Row],[Miasto (City)]] -> Gdańsk | G4: =Raw_Data[[#This Row],[Ilość (Quant.)]] -> 3 | H4: =Raw_Data[[#This Row],[Przychód brutto (Revenue)]] -> 23.803333 | I4: =(Raw_Data[[#This Row],[Przychód brutto (Revenue)]]-_xlfn.XLOOKUP(Raw_Data[[#This Row],[Produkt (Product)]],'Product lookup table'!$A$2:$A$20,'Product lookup table'!$C$2:$C$20)*Raw_Data[[#This Row],[Ilość (Quant.)]]) - (Raw_Data[[#This Row],[Przychód brutto (Revenue)]]*_xlfn.XLOOKUP(Processed_data[[#This Row],[Kanał sprzedaży (Marketplace)]],'Założenia (Assumptions)'!$B$4:$B$7,'Założenia (Assumptions)'!$C$4:$C$7)) -> 14.399067 | J4: =Processed_data[[#This Row],[Zysk brutto (Gross profit)]]/Processed_data[[#This Row],[Przychód brutto (Revenue)]] -> 0.60491808 | K4: =IF(Processed_data[[#This Row],[Marża (Margin)]]>0.6,"wysoka",IF(Processed_data[[#This Row],[Marża (Margin)]]>0.3,"średnia","niska")) -> wysoka | L4: =MONTH(Raw_Data[[#This Row],[Data zamów. (Order date)]]) -> 5 | M4: =TEXT(Raw_Data[[#This Row],[Data zamów. (Order date)]], "MMMM") -> maj | N4: =IF(Processed_data[[#This Row],[Miesiąc (Month)]]<=3,1,IF(Processed_data[[#This Row],[Miesiąc (Month)]]<=6,2,IF(Processed_data[[#This Row],[Miesiąc (Month)]]<=9,3,4))) -> 2
A5: =Raw_Data[[#This Row],[ID zamów. (Order ID)]] -> ORD0004 | B5: =Raw_Data[[#This Row],[ID klienta (Client ID)]] -> CUST7053 | C5: =_xlfn.XLOOKUP(Raw_Data[[#This Row],[Produkt (Product)]],'Product lookup table'!$A$2:$A$20,'Product lookup table'!$B$2:$B$20) -> Elektronika | D5: =Raw_Data[[#This Row],[Produkt (Product)]] -> Powerbank | E5: =Raw_Data[[#This Row],[Kanał sprzedaży (Marketplace)]] -> Amazon | F5: =Raw_Data[[#This Row],[Miasto (City)]] -> Gdańsk | G5: =Raw_Data[[#This Row],[Ilość (Quant.)]] -> 1 | H5: =Raw_Data[[#This Row],[Przychód brutto (Revenue)]] -> 99.620435 | I5: =(Raw_Data[[#This Row],[Przychód brutto (Revenue)]]-_xlfn.XLOOKUP(Raw_Data[[#This Row],[Produkt (Product)]],'Product lookup table'!$A$2:$A$20,'Product lookup table'!$C$2:$C$20)*Raw_Data[[#This Row],[Ilość (Quant.)]]) - (Raw_Data[[#This Row],[Przychód brutto (Revenue)]]*_xlfn.XLOOKUP(Processed_data[[#This Row],[Kanał sprzedaży (Marketplace)]],'Założenia (Assumptions)'!$B$4:$B$7,'Założenia (Assumptions)'!$C$4:$C$7)) -> 7.6659826 | J5: =Processed_data[[#This Row],[Zysk brutto (Gross profit)]]/Processed_data[[#This Row],[Przychód brutto (Revenue)]] -> 0.076951909 | K5: =IF(Processed_data[[#This Row],[Marża (Margin)]]>0.6,"wysoka",IF(Processed_data[[#This Row],[Marża (Margin)]]>0.3,"średnia","niska")) -> niska | L5: =MONTH(Raw_Data[[#This Row],[Data zamów. (Order date)]]) -> 2 | M5: =TEXT(Raw_Data[[#This Row],[Data zamów. (Order date)]], "MMMM") -> luty | N5: =IF(Processed_data[[#This Row],[Miesiąc (Month)]]<=3,1,IF(Processed_data[[#This Row],[Miesiąc (Month)]]<=6,2,IF(Processed_data[[#This Row],[Miesiąc (Month)]]<=9,3,4))) -> 1
A6: =Raw_Data[[#This Row],[ID zamów. (Order ID)]] -> ORD0005 | B6: =Raw_Data[[#This Row],[ID klienta (Client ID)]] -> CUST3810 | C6: =_xlfn.XLOOKUP(Raw_Data[[#This Row],[Produkt (Product)]],'Product lookup table'!$A$2:$A$20,'Product lookup table'!$B$2:$B$20) -> Outdoor | D6: =Raw_Data[[#This Row],[Produkt (Product)]] -> Buty trekkingowe | E6: =Raw_Data[[#This Row],[Kanał sprzedaży (Marketplace)]] -> Amazon | F6: =Raw_Data[[#This Row],[Miasto (City)]] -> Poznań | G6: =Raw_Data[[#This Row],[Ilość (Quant.)]] -> 2 | H6: =Raw_Data[[#This Row],[Przychód brutto (Revenue)]] -> 1019.6514 | I6: =(Raw_Data[[#This Row],[Przychód brutto (Revenue)]]-_xlfn.XLOOKUP(Raw_Data[[#This Row],[Produkt (Product)]],'Product lookup table'!$A$2:$A$20,'Product lookup table'!$C$2:$C$20)*Raw_Data[[#This Row],[Ilość (Quant.)]]) - (Raw_Data[[#This Row],[Przychód brutto (Revenue)]]*_xlfn.XLOOKUP(Processed_data[[#This Row],[Kanał sprzedaży (Marketplace)]],'Założenia (Assumptions)'!$B$4:$B$7,'Założenia (Assumptions)'!$C$4:$C$7)) -> 277.29326 | J6: =Processed_data[[#This Row],[Zysk brutto (Gross profit)]]/Processed_data[[#This Row],[Przychód brutto (Revenue)]] -> 0.27194907 | K6: =IF(Processed_data[[#This Row],[Marża (Margin)]]>0.6,"wysoka",IF(Processed_data[[#This Row],[Marża (Margin)]]>0.3,"średnia","niska")) -> niska | L6: =MONTH(Raw_Data[[#This Row],[Data zamów. (Order date)]]) -> 11 | M6: =TEXT(Raw_Data[[#This Row],[Data zamów. (Order date)]], "MMMM") -> listopad | N6: =IF(Processed_data[[#This Row],[Miesiąc (Month)]]<=3,1,IF(Processed_data[[#This Row],[Miesiąc (Month)]]<=6,2,IF(Processed_data[[#This Row],[Miesiąc (Month)]]<=9,3,4))) -> 4
A7: =Raw_Data[[#This Row],[ID zamów. (Order ID)]] -> ORD0006 | B7: =Raw_Data[[#This Row],[ID klienta (Client ID)]] -> CUST3810 | C7: =_xlfn.XLOOKUP(Raw_Data[[#This Row],[Produkt (Product)]],'Product lookup table'!$A$2:$A$20,'Product lookup table'!$B$2:$B$20) -> Kosmetyki | D7: =Raw_Data[[#This Row],[Produkt (Product)]] -> Szampon | E7: =Raw_Data[[#This Row],[Kanał sprzedaży (Marketplace)]] -> Allegro | F7: =Raw_Data[[#This Row],[Miasto (City)]] -> Poznań | G7: =Raw_Data[[#This Row],[Ilość (Quant.)]] -> 5 | H7: =Raw_Data[[#This Row],[Przychód brutto (Revenue)]] -> 36.575 | I7: =(Raw_Data[[#This Row],[Przychód brutto (Revenue)]]-_xlfn.XLOOKUP(Raw_Data[[#This Row],[Produkt (Product)]],'Product lookup table'!$A$2:$A$20,'Product lookup table'!$C$2:$C$20)*Raw_Data[[#This Row],[Ilość (Quant.)]]) - (Raw_Data[[#This Row],[Przychód brutto (Revenue)]]*_xlfn.XLOOKUP(Processed_data[[#This Row],[Kanał sprzedaży (Marketplace)]],'Założenia (Assumptions)'!$B$4:$B$7,'Założenia (Assumptions)'!$C$4:$C$7)) -> 16.149 | J7: =Processed_data[[#This Row],[Zysk brutto (Gross profit)]]/Processed_data[[#This Row],[Przychód brutto (Revenue)]] -> 0.4415311 | K7: =IF(Processed_data[[#This Row],[Marża (Margin)]]>0.6,"wysoka",IF(Processed_data[[#This Row],[Marża (Margin)]]>0.3,"średnia","niska")) -> średnia | L7: =MONTH(Raw_Data[[#This Row],[Data zamów. (Order date)]]) -> 10 | M7: =TEXT(Raw_Data[[#This Row],[Data zamów. (Order date)]], "MMMM") -> październik | N7: =IF(Processed_data[[#This Row],[Miesiąc (Month)]]<=3,1,IF(Processed_data[[#This Row],[Miesiąc (Month)]]<=6,2,IF(Processed_data[[#This Row],[Miesiąc (Month)]]<=9,3,4))) -> 4
A8: =Raw_Data[[#This Row],[ID zamów. (Order ID)]] -> ORD0007 | B8: =Raw_Data[[#This Row],[ID klienta (Client ID)]] -> CUST3810 | C8: =_xlfn.XLOOKUP(Raw_Data[[#This Row],[Produkt (Product)]],'Product lookup table'!$A$2:$A$20,'Product lookup table'!$B$2:$B$20) -> Home | D8: =Raw_Data[[#This Row],[Produkt (Product)]] -> Świeca zapachowa | E8: =Raw_Data[[#This Row],[Kanał sprzedaży (Marketplace)]] -> Allegro | F8: =Raw_Data[[#This Row],[Miasto (City)]] -> Poznań | G8: =Raw_Data[[#This Row],[Ilość (Quant.)]] -> 4 | H8: =Raw_Data[[#This Row],[Przychód brutto (Revenue)]] -> 187.23273 | I8: =(Raw_Data[[#This Row],[Przychód brutto (Revenue)]]-_xlfn.XLOOKUP(Raw_Data[[#This Row],[Produkt (Product)]],'Product lookup table'!$A$2:$A$20,'Product lookup table'!$C$2:$C$20)*Raw_Data[[#This Row],[Ilość (Quant.)]]) - (Raw_Data[[#This Row],[Przychód brutto (Revenue)]]*_xlfn.XLOOKUP(Processed_data[[#This Row],[Kanał sprzedaży (Marketplace)]],'Założenia (Assumptions)'!$B$4:$B$7,'Założenia (Assumptions)'!$C$4:$C$7)) -> 92.254109 | J8: =Processed_data[[#This Row],[Zysk brutto (Gross profit)]]/Processed_data[[#This Row],[Przychód brutto (Revenue)]] -> 0.49272427 | K8: =IF(Processed_data[[#This Row],[Marża (Margin)]]>0.6,"wysoka",IF(Processed_data[[#This Row],[Marża (Margin)]]>0.3,"średnia","niska")) -> średnia | L8: =MONTH(Raw_Data[[#This Row],[Data zamów. (Order date)]]) -> 5 | M8: =TEXT(Raw_Data[[#This Row],[Data zamów. (Order date)]], "MMMM") -> maj | N8: =IF(Processed_data[[#This Row],[Miesiąc (Month)]]<=3,1,IF(Processed_data[[#This Row],[Miesiąc (Month)]]<=6,2,IF(Processed_data[[#This Row],[Miesiąc (Month)]]<=9,3,4))) -> 2
A9: =Raw_Data[[#This Row],[ID zamów. (Order ID)]] -> ORD0008 | B9: =Raw_Data[[#This Row],[ID klienta (Client ID)]] -> CUST3810 | C9: =_xlfn.XLOOKUP(Raw_Data[[#This Row],[Produkt (Product)]],'Product lookup table'!$A$2:$A$20,'Product lookup table'!$B$2:$B$20) -> Kosmetyki | D9: =Raw_Data[[#This Row],[Produkt (Product)]] -> Krem do twarzy | E9: =Raw_Data[[#This Row],[Kanał sprzedaży (Marketplace)]] -> Amazon | F9: =Raw_Data[[#This Row],[Miasto (City)]] -> Poznań | G9: =Raw_Data[[#This Row],[Ilość (Quant.)]] -> 1 | H9: =Raw_Data[[#This Row],[Przychód brutto (Revenue)]] -> 51.369278 | I9: =(Raw_Data[[#This Row],[Przychód brutto (Revenue)]]-_xlfn.XLOOKUP(Raw_Data[[#This Row],[Produkt (Product)]],'Product lookup table'!$A$2:$A$20,'Product lookup table'!$C$2:$C$20)*Raw_Data[[#This Row],[Ilość (Quant.)]]) - (Raw_Data[[#This Row],[Przychód brutto (Revenue)]]*_xlfn.XLOOKUP(Processed_data[[#This Row],[Kanał sprzedaży (Marketplace)]],'Założenia (Assumptions)'!$B$4:$B$7,'Założenia (Assumptions)'!$C$4:$C$7)) -> 20.204964 | J9: =Processed_data[[#This Row],[Zysk brutto (Gross profit)]]/Processed_data[[#This Row],[Przychód brutto (Revenue)]] -> 0.39332779 | K9: =IF(Processed_data[[#This Row],[Marża (Margin)]]>0.6,"wysoka",IF(Processed_data[[#This Row],[Marża (Margin)]]>0.3,"średnia","niska")) -> średnia | L9: =MONTH(Raw_Data[[#This Row],[Data zamów. (Order date)]]) -> 4 | M9: =TEXT(Raw_Data[[#This Row],[Data zamów. (Order date)]], "MMMM") -> kwiecień | N9: =IF(Processed_data[[#This Row],[Miesiąc (Month)]]<=3,1,IF(Processed_data[[#This Row],[Miesiąc (Month)]]<=6,2,IF(Processed_data[[#This Row],[Miesiąc (Month)]]<=9,3,4))) -> 2
A10: =Raw_Data[[#This Row],[ID zamów. (Order ID)]] -> ORD0009 | B10: =Raw_Data[[#This Row],[ID klienta (Client ID)]] -> CUST3810 | C10: =_xlfn.XLOOKUP(Raw_Data[[#This Row],[Produkt (Product)]],'Product lookup table'!$A$2:$A$20,'Product lookup table'!$B$2:$B$20) -> Kosmetyki | D10: =Raw_Data[[#This Row],[Produkt (Product)]] -> Serum | E10: =Raw_Data[[#This Row],[Kanał sprzedaży (Marketplace)]] -> Amazon | F10: =Raw_Data[[#This Row],[Miasto (City)]] -> Poznań | G10: =Raw_Data[[#This Row],[Ilość (Quant.)]] -> 4 | H10: =Raw_Data[[#This Row],[Przychód brutto (Revenue)]] -> 330.66333 | I10: =(Raw_Data[[#This Row],[Przychód brutto (Revenue)]]-_xlfn.XLOOKUP(Raw_Data[[#This Row],[Produkt (Product)]],'Product lookup table'!$A$2:$A$20,'Product lookup table'!$C$2:$C$20)*Raw_Data[[#This Row],[Ilość (Quant.)]]) - (Raw_Data[[#This Row],[Przychód brutto (Revenue)]]*_xlfn.XLOOKUP(Processed_data[[#This Row],[Kanał sprzedaży (Marketplace)]],'Założenia (Assumptions)'!$B$4:$B$7,'Założenia (Assumptions)'!$C$4:$C$7)) -> 170.98373 | J10: =Processed_data[[#This Row],[Zysk brutto (Gross profit)]]/Processed_data[[#This Row],[Przychód brutto (Revenue)]] -> 0.51709312 | K10: =IF(Processed_data[[#This Row],[Marża (Margin)]]>0.6,"wysoka",IF(Processed_data[[#This Row],[Marża (Margin)]]>0.3,"średnia","niska")) -> średnia | L10: =MONTH(Raw_Data[[#This Row],[Data zamów. (Order date)]]) -> 8 | M10: =TEXT(Raw_Data[[#This Row],[Data zamów. (Order date)]], "MMMM") -> sierpień | N10: =IF(Processed_data[[#This Row],[Miesiąc (Month)]]<=3,1,IF(Processed_data[[#This Row],[Miesiąc (Month)]]<=6,2,IF(Processed_data[[#This Row],[Miesiąc (Month)]]<=9,3,4))) -> 3
A11: =Raw_Data[[#This Row],[ID zamów. (Order ID)]] -> ORD0010 | B11: =Raw_Data[[#This Row],[ID klienta (Client ID)]] -> CUST6724 | C11: =_xlfn.XLOOKUP(Raw_Data[[#This Row],[Produkt (Product)]],'Product lookup table'!$A$2:$A$20,'Product lookup table'!$B$2:$B$20) -> Outdoor | D11: =Raw_Data[[#This Row],[Produkt (Product)]] -> Namiot | E11: =Raw_Data[[#This Row],[Kanał sprzedaży (Marketplace)]] -> Empik Marketplace | F11: =Raw_Data[[#This Row],[Miasto (City)]] -> Kraków | G11: =Raw_Data[[#This Row],[Ilość (Quant.)]] -> 4 | H11: =Raw_Data[[#This Row],[Przychód brutto (Revenue)]] -> 2266.8171 | I11: =(Raw_Data[[#This Row],[Przychód brutto (Revenue)]]-_xlfn.XLOOKUP(Raw_Data[[#This Row],[Produkt (Product)]],'Product lookup table'!$A$2:$A$20,'Product lookup table'!$C$2:$C$20)*Raw_Data[[#This Row],[Ilość (Quant.)]]) - (Raw_Data[[#This Row],[Przychód brutto (Revenue)]]*_xlfn.XLOOKUP(Processed_data[[#This Row],[Kanał sprzedaży (Marketplace)]],'Założenia (Assumptions)'!$B$4:$B$7,'Założenia (Assumptions)'!$C$4:$C$7)) -> 600.13543 | J11: =Processed_data[[#This Row],[Zysk brutto (Gross profit)]]/Processed_data[[#This Row],[Przychód brutto (Revenue)]] -> 0.26474805 | K11: =IF(Processed_data[[#This Row],[Marża (Margin)]]>0.6,"wysoka",IF(Processed_data[[#This Row],[Marża (Margin)]]>0.3,"średnia","niska")) -> niska | L11: =MONTH(Raw_Data[[#This Row],[Data zamów. (Order date)]]) -> 9 | M11: =TEXT(Raw_Data[[#This Row],[Data zamów. (Order date)]], "MMMM") -> wrzesień | N11: =IF(Processed_data[[#This Row],[Miesiąc (Month)]]<=3,1,IF(Processed_data[[#This Row],[Miesiąc (Month)]]<=6,2,IF(Processed_data[[#This Row],[Miesiąc (Month)]]<=9,3,4))) -> 3
A12: =Raw_Data[[#This Row],[ID zamów. (Order ID)]] -> ORD0011 | B12: =Raw_Data[[#This Row],[ID klienta (Client ID)]] -> CUST6724 | C12: =_xlfn.XLOOKUP(Raw_Data[[#This Row],[Produkt (Product)]],'Product lookup table'!$A$2:$A$20,'Product lookup table'!$B$2:$B$20) -> Kosmetyki | D12: =Raw_Data[[#This Row],[Produkt (Product)]] -> Paleta cieni | E12: =Raw_Data[[#This Row],[Kanał sprzedaży (Marketplace)]] -> Allegro | F12: =Raw_Data[[#This Row],[Miasto (City)]] -> Kraków | G12: =Raw_Data[[#This Row],[Ilość (Quant.)]] -> 1 | H12: =Raw_Data[[#This Row],[Przychód brutto (Revenue)]] -> 88.711 | I12: =(Raw_Data[[#This Row],[Przychód brutto (Revenue)]]-_xlfn.XLOOKUP(Raw_Data[[#This Row],[Produkt (Product)]],'Product lookup table'!$A$2:$A$20,'Product lookup table'!$C$2:$C$20)*Raw_Data[[#This Row],[Ilość (Quant.)]]) - (Raw_Data[[#This Row],[Przychód brutto (Revenue)]]*_xlfn.XLOOKUP(Processed_data[[#This Row],[Kanał sprzedaży (Marketplace)]],'Założenia (Assumptions)'!$B$4:$B$7,'Założenia (Assumptions)'!$C$4:$C$7)) -> 41.61412 | J12: =Processed_data[[#This Row],[Zysk brutto (Gross profit)]]/Processed_data[[#This Row],[Przychód brutto (Revenue)]] -> 0.46909763 | K12: =IF(Processed_data[[#This Row],[Marża (Margin)]]>0.6,"wysoka",IF(Processed_data[[#This Row],[Marża (Margin)]]>0.3,"średnia","niska")) -> średnia | L12: =MONTH(Raw_Data[[#This Row],[Data zamów. (Order date)]]) -> 1 | M12: =TEXT(Raw_Data[[#This Row],[Data zamów. (Order date)]], "MMMM") -> styczeń | N12: =IF(Processed_data[[#This Row],[Miesiąc (Month)]]<=3,1,IF(Processed_data[[#This Row],[Miesiąc (Month)]]<=6,2,IF(Processed_data[[#This Row],[Miesiąc (Month)]]<=9,3,4))) -> 1
A13: =Raw_Data[[#This Row],[ID zamów. (Order ID)]] -> ORD0012 | B13: =Raw_Data[[#This Row],[ID klienta (Client ID)]] -> CUST6724 | C13: =_xlfn.XLOOKUP(Raw_Data[[#This Row],[Produkt (Product)]],'Product lookup table'!$A$2:$A$20,'Product lookup table'!$B$2:$B$20) -> Home | D13: =Raw_Data[[#This Row],[Produkt (Product)]] -> Poduszka dekoracyjna | E13: =Raw_Data[[#This Row],[Kanał sprzedaży (Marketplace)]] -> Amazon | F13: =Raw_Data[[#This Row],[Miasto (City)]] -> Kraków | G13: =Raw_Data[[#This Row],[Ilość (Quant.)]] -> 4 | H13: =Raw_Data[[#This Row],[Przychód brutto (Revenue)]] -> 197.21891 | I13: =(Raw_Data[[#This Row],[Przychód brutto (Revenue)]]-_xlfn.XLOOKUP(Raw_Data[[#This Row],[Produkt (Product)]],'Product lookup table'!$A$2:$A$20,'Product lookup table'!$C$2:$C$20)*Raw_Data[[#This Row],[Ilość (Quant.)]]) - (Raw_Data[[#This Row],[Przychód brutto (Revenue)]]*_xlfn.XLOOKUP(Processed_data[[#This Row],[Kanał sprzedaży (Marketplace)]],'Założenia (Assumptions)'!$B$4:$B$7,'Założenia (Assumptions)'!$C$4:$C$7)) -> 53.55264 | J13: =Processed_data[[#This Row],[Zysk brutto (Gross profit)]]/Processed_data[[#This Row],[Przychód brutto (Revenue)]] -> 0.27153907 | K13: =IF(Processed_data[[#This Row],[Marża (Margin)]]>0.6,"wysoka",IF(Processed_data[[#This Row],[Marża (Margin)]]>0.3,"średnia","niska")) -> niska | L13: =MONTH(Raw_Data[[#This Row],[Data zamów. (Order date)]]) -> 12 | M13: =TEXT(Raw_Data[[#This Row],[Data zamów. (Order date)]], "MMMM") -> grudzień | N13: =IF(Processed_data[[#This Row],[Miesiąc (Month)]]<=3,1,IF(Processed_data[[#This Row],[Miesiąc (Month)]]<=6,2,IF(Processed_data[[#This Row],[Miesiąc (Month)]]<=9,3,4))) -> 4
... A201: =Raw_Data[[#This Row],[ID zamów. (Order ID)]] -> ORD0200 | B201: =Raw_Data[[#This Row],[ID klienta (Client ID)]] -> CUST7053 | C201: =_xlfn.XLOOKUP(Raw_Data[[#This Row],[Produkt (Product)]],'Product lookup table'!$A$2:$A$20,'Product lookup table'!$B$2:$B$20) -> Kosmetyki | D201: =Raw_Data[[#This Row],[Produkt (Product)]] -> Olejek | E201: =Raw_Data[[#This Row],[Kanał sprzedaży (Marketplace)]] -> Amazon | F201: =Raw_Data[[#This Row],[Miasto (City)]] -> Gdańsk | G201: =Raw_Data[[#This Row],[Ilość (Quant.)]] -> 5 | H201: =Raw_Data[[#This Row],[Przychód brutto (Revenue)]] -> 48.955556 | I201: =(Raw_Data[[#This Row],[Przychód brutto (Revenue)]]-_xlfn.XLOOKUP(Raw_Data[[#This Row],[Produkt (Product)]],'Product lookup table'!$A$2:$A$20,'Product lookup table'!$C$2:$C$20)*Raw_Data[[#This Row],[Ilość (Quant.)]]) - (Raw_Data[[#This Row],[Przychód brutto (Revenue)]]*_xlfn.XLOOKUP(Processed_data[[#This Row],[Kanał sprzedaży (Marketplace)]],'Założenia (Assumptions)'!$B$4:$B$7,'Założenia (Assumptions)'!$C$4:$C$7)) -> 18.080889 | J201: =Processed_data[[#This Row],[Zysk brutto (Gross profit)]]/Processed_data[[#This Row],[Przychód brutto (Revenue)]] -> 0.36933273 | K201: =IF(Processed_data[[#This Row],[Marża (Margin)]]>0.6,"wysoka",IF(Processed_data[[#This Row],[Marża (Margin)]]>0.3,"średnia","niska")) -> średnia | L201: =MONTH(Raw_Data[[#This Row],[Data zamów. (Order date)]]) -> 12 | M201: =TEXT(Raw_Data[[#This Row],[Data zamów. (Order date)]], "MMMM") -> grudzień | N201: =IF(Processed_data[[#This Row],[Miesiąc (Month)]]<=3,1,IF(Processed_data[[#This Row],[Miesiąc (Month)]]<=6,2,IF(Processed_data[[#This Row],[Miesiąc (Month)]]<=9,3,4))) -> 4
A202: =SUBTOTAL(103,Processed_data[ID zamów. (Order ID)]) -> 200 | B202: {=INDEX(Processed_data[ID klienta (Client ID)], _xlfn.MODE.SNGL(_xlfn.XMATCH(Processed_data[ID klienta (Client ID)],Processed_data[ID klienta (Client ID)],0)))} -> CUST1476 | C202: {=INDEX(Processed_data[Kategoria (Category)], _xlfn.MODE.SNGL(_xlfn.XMATCH(Processed_data[Kategoria (Category)],Processed_data[Kategoria (Category)],0)))} -> Kosmetyki | D202: {=INDEX(Processed_data[Produkt (Product)], _xlfn.MODE.SNGL(_xlfn.XMATCH(Processed_data[Produkt (Product)],Processed_data[Produkt (Product)],0)))} -> Namiot | E202: {=INDEX(Processed_data[Kanał sprzedaży (Marketplace)], _xlfn.MODE.SNGL(_xlfn.XMATCH(Processed_data[Kanał sprzedaży (Marketplace)],Processed_data[Kanał sprzedaży (Marketplace)],0)))} -> Allegro | F202: {=INDEX(Processed_data[Miasto (City)], _xlfn.MODE.SNGL(_xlfn.XMATCH(Processed_data[Miasto (City)],Processed_data[Miasto (City)],0)))} -> Warszawa | G202: =SUBTOTAL(109,Processed_data[Ilość (Quant.)]) -> 613 | H202: =SUBTOTAL(101,Processed_data[Przychód brutto (Revenue)]) -> 443.53621 | I202: =SUBTOTAL(109,Processed_data[Zysk brutto (Gross profit)]) -> 27503.094 | J202: =SUBTOTAL(101,Processed_data[Marża (Margin)]) -> 0.38210583 | K202: {=INDEX(Processed_data[Kat. marży (Margin category)], _xlfn.MODE.SNGL(_xlfn.XMATCH(Processed_data[Kat. marży (Margin category)],Processed_data[Kat. marży (Margin category)],0)))} -> średnia | L202: {=INDEX(Processed_data[Miesiąc (Month)], _xlfn.MODE.SNGL(_xlfn.XMATCH(Processed_data[Miesiąc (Month)],Processed_data[Miesiąc (Month)],0)))} -> 12 | M202: {=INDEX(Processed_data[Miesiąc (Month)2], _xlfn.MODE.SNGL(_xlfn.XMATCH(Processed_data[Miesiąc (Month)2],Processed_data[Miesiąc (Month)2],0)))} -> grudzień | N202: {=INDEX(Processed_data[Kwartał (Quarter)], _xlfn.MODE.SNGL(_xlfn.XMATCH(Processed_data[Kwartał (Quarter)],Processed_data[Kwartał (Quarter)],0)))} -> 4

Sheet Analiza (Analysis)
B3: Etykiety wierszy | C3: Suma zysków brutto | D3: Suma przychodów brutto | E3: Średnia marża | F3: Ilość
B4: Allegro | C4: 8879.9035 | D4: 28732.504 | E4: 0.39026204 | F4: 174
B5: Empik Marketplace | C5: 8620.811 | D5: 29159.234 | E5: 0.35405632 | F5: 173
B6: Amazon | C6: 5565.5688 | D6: 20255.192 | E6: 0.33238012 | F6: 140
B7: Shopify | C7: 4436.8111 | D7: 10560.311 | E7: 0.47016922 | F7: 126
B8: Suma końcowa | C8: 27503.094 | D8: 88707.241 | E8: 0.38210583 | F8: =AVERAGE(F4:F7) -> 153.25
B10: Etykiety wierszy | C10: Suma zysków brutto | D10: Suma przychodów brutto | E10: Średnia marża | F10: Ilość
B11: Outdoor | C11: 19439.239 | D11: 64789.817 | E11: 0.30805799 | F11: 214
B12: Kosmetyki | C12: 5630.3237 | D12: 10616.09 | E12: 0.53716647 | F12: 234
B13: Home | C13: 1460.8346 | D13: 3144.7503 | E13: 0.46104742 | F13: 78
B14: Elektronika | C14: 972.69657 | D14: 10156.583 | E14: 0.08940855 | F14: 87
B15: Suma końcowa | C15: 27503.094 | D15: 88707.241 | E15: 0.38210583 | F15: =AVERAGE(F11:F14) -> 153.25
B17: Etykiety wierszy | C17: Suma zysków brutto | D17: Suma przychodów brutto | E17: Ilość | F17: Udział w przychodzie | G17: Miasto
B18: Warszawa | C18: 6310.4712 | D18: 20497.267 | E18: 171 | F18: =C18/GETPIVOTDATA("Suma zysków brutto",$B$17) -> 0.22944586 | G18: Warszawa
B19: Wrocław | C19: 5609.0988 | D19: 19745.094 | E19: 89 | F19: =C19/GETPIVOTDATA("Suma zysków brutto",$B$17) -> 0.20394428 | G19: Wrocław
B20: Gdańsk | C20: 5176.3632 | D20: 13950.474 | E20: 105 | F20: =C20/GETPIVOTDATA("Suma zysków brutto",$B$17) -> 0.18821021 | G20: Gdańsk
B21: Poznań | C21: 4858.6102 | D21: 15411.592 | E21: 92 | F21: =C21/GETPIVOTDATA("Suma zysków brutto",$B$17) -> 0.17665686 | G21: Poznań
B22: Kraków | C22: 3975.7604 | D22: 13605.533 | E22: 118 | F22: =C22/GETPIVOTDATA("Suma zysków brutto",$B$17) -> 0.14455684 | G22: Kraków
B23: Łódź | C23: 1572.7906 | D23: 5497.2805 | E23: 38 | F23: =C23/GETPIVOTDATA("Suma zysków brutto",$B$17) -> 0.057185949 | G23: Łódź
B24: Suma końcowa | C24: 27503.094 | D24: 88707.241 | E24: 613
B26: Etykiety wierszy | C26: Suma przychodów brutto | D26: Suma zysków brutto | F26: Przychód brutto | G26: ='Dane przetw. (Processed data)'!H202 -> 443.53621
B27: styczeń | C27: 4246.6703 | D27: 1860.4113
B28: luty | C28: 8073.1114 | D28: 2754.3699
B29: marzec | C29: 3378.5373 | D29: 1068.5225 | F29: Zysk brutto | G29: ='Dane przetw. (Processed data)'!I202 -> 27503.094
B30: kwiecień | C30: 5877.5241 | D30: 1826.1644
B31: maj | C31: 10091.028 | D31: 2778.8613
B32: czerwiec | C32: 6251.3309 | D32: 2210.1044 | F32: Średnia marża | G32: ='Dane przetw. (Processed data)'!J202 -> 0.38210583
B33: lipiec | C33: 7033.3956 | D33: 2194.3304
B34: sierpień | C34: 5081.7455 | D34: 1752.6719
B35: wrzesień | C35: 9361.7542 | D35: 2691.3516 | F35: AOV | G35: ='Dane przetw. (Processed data)'!H202 -> 443.53621
B36: październik | C36: 7428.6995 | D36: 1864.1318
B37: listopad | C37: 9500.8851 | D37: 2630.0294
B38: grudzień | C38: 12382.56 | D38: 3872.1454
B39: Suma końcowa | C39: 88707.241 | D39: 27503.094

Sheet Dashboard

Sheet Wnioski
A1: W analizowanym okresie (styczeń-grudzień 2025) sklep MultiShop wygenerował łączny przychód brutto 88 707 zł przy zysku brutto 27 503 zł i średniej marży 38,21%. Średnia wartość zamówienia (AOV) wyniosła około 444 zł. Kategorią o najwyższym zysku bezwzględnym był Outdoor (19 439 zł), natomiast najwyższą efektywność kosztową osiągnęła kategoria Kosmetyki (marża 54%). Kanały sprzedaży Mimo że Empik Marketplace osiąga najwyższy przychód brutto, Allegro generuje wyższy zysk dzięki niższej prowizji platformy (8% vs 10%). Shopify przy najmniejszym wolumenie sprzedaży utrzymuje najwyższą marżę (47%) co sugeruje, że rozwój własnego kanału sprzedaży byłby strategicznie korzystny dla rentowności biznesu. Amazon wykazuje najmniej korzystny profil spośród wszystkich kanałów – trzeci wynik pod względem wolumenu sprzedaży (140 sztuk) przy jednocześnie najniższej marży (33%). Wyniki sugerują potrzebę weryfikacji opłacalności kanału lub/i rozważenie ograniczenia asortymentu do kategorii produktów o najwyższej marży (kosmetyki, home). Kategorie produktów Outdoor generuje najwyższy zysk bezwzględny, dzięki największemu wolumenowi sprzedaży (214 sztuk) i przychodowi brutto. Mimo niewysokiej marży skala sprzedaży przekłada się na solidny wynik. Kosmetyki to najbardziej efektywna kosztowo kategoria, gdzie ponad połowa przychodu staje się zyskiem. Home przy najniższym wolumenie (78 sztuk) utrzymuje wysoką marżę, generując proporcjonalnie dobry wynik. Elektronika wypada najsłabiej. Mimo wysokiego przychodu brutto zysk jest najniższy, co wynika z wysokich COGSów i prowizji platform. Wyniki sugerują potrzebę weryfikacji opłacalności – rozważenie wycofania jej z kanałów o najwyższych prowizjach oraz zastosowanie mechanizmów zwiększających wartość koszyka, np. promocji wielosztukowych, które pozwoliłyby rozłożyć stałe koszty na większą liczbę jednostek w zamówieniu. Geografia Warszawa dominuje pod względem wolumenu zamówień (171 sztuk) i przychodu brutto (20 497 zł), odpowiadając za 23% całkowitego przychodu. Wrocław zajmuje drugą pozycję z przychodem 19 745 zł i udziałem 20%, jednak przy znacznie niższym wolumenie (89 sztuk), co oznacza że średnia wartość zamówienia we Wrocławiu jest wyraźnie wyższa niż w Warszawie. Gdańsk, Poznań i Kraków generują zbliżone wyniki zarówno pod względem wolumenu jak i przychodu, tworząc środkowy segment bez wyraźnego lidera. Łódź wypada najsłabiej – 38 zamówień i 6% udziału w przychodzie. To może wskazywać na niższe nasycenie rynku lub słabszą widoczność oferty w tym mieście – warto rozważyć zbadanie widoczności oferty i kampanie targetowane geograficznie. Trend miesięczny Przychód i zysk wykazują wyraźną sezonowość w ciągu roku. Pierwsze szczyty sprzedażowe przypadają na luty (walentynki) i maj. Sprzedaż w maju prawdopodobnie napędzana jest przez wzmożony popyt na produkty outdoorowe wraz z nadejściem sezonu wiosenno-letniego. Letnie miesiące przynoszą spadek aktywności zakupowej. Wyraźne odbicie następuje od września, a szczyt roku przypada na listopad-grudzień. Okres przedświąteczny i Black Friday generują najwyższe przychody i zyski w całym roku, z grudniem jako bezwzględnym liderem (12 383 zł przychodu, 3 872 zł zysku). Dane historyczne sugerują, że zwiększenie stanów magazynowych przed majem oraz przed czwartym kwartałem mogłoby przynieść wymierne korzyści.
